strings_fuzz/__init__.py
strings_fuzz/analyzer.py
strings_fuzz/cleaner.py
strings_fuzz/matcher/__init__.py
strings_fuzz-0.0.6.dist-info/LICENSE
strings_fuzz-0.0.6.dist-info/METADATA
strings_fuzz-0.0.6.dist-info/WHEEL
strings_fuzz-0.0.6.dist-info/top_level.txt
strings_fuzz-0.0.6.dist-info/RECORD
