Metadata-Version: 2.1
Name: strings-fuzz
Version: 0.0.6
Summary: A flexible fuzzy name matcher, with multi-language support, that finds best matches between two sets using the edit distance method
Home-page: https://github.com/tigeryst/strings-fuzz
Author: Tiger Yotsawat
Author-email: tigeryotsawat@gmail.com
License: UNKNOWN
Project-URL: Bug Tracker, https://github.com/tigeryst/strings-fuzz/issues
Keywords: fuzzy,Levenshtein,matcher
Platform: UNKNOWN
Classifier: Programming Language :: Python :: 3
Classifier: License :: OSI Approved :: MIT License
Classifier: Operating System :: OS Independent
Requires-Python: >=3.6
License-File: LICENSE
Requires-Dist: fuzzywuzzy (~=0.18.0)
Requires-Dist: num2words (~=0.5.10)
Requires-Dist: python-Levenshtein (~=0.12.2)
Requires-Dist: pythainlp (~=3.0.5)
Requires-Dist: pandas (~=1.4.2)
Requires-Dist: numpy (~=1.22.3)
Provides-Extra: test
Requires-Dist: pytest (>=7.1.2) ; extra == 'test'
